itinerary/__init__.py
itinerary/migration.py
pgmigrator/__init__.py
pgmigrator/migration.py
itinerary-1.0.1.dist-info/LICENSE.md
itinerary-1.0.1.dist-info/METADATA
itinerary-1.0.1.dist-info/WHEEL
itinerary-1.0.1.dist-info/top_level.txt
itinerary-1.0.1.dist-info/RECORD
