Metadata-Version: 2.1
Name: itinerary
Version: 1.0.1
Summary: A tool to apply pure SQL migrations to PostgreSQL databases at runtime.
Home-page: https://github.com/awkspace/itinerary
Author: awk
Author-email: awk@awk.space
License: MIT
Platform: UNKNOWN
Requires-Dist: psycopg2
